README.md
setup.py
test/test.py
utilitybox/__init__.py
utilitybox/__main__.py
utilitybox/utilitybox.py
utilitybox.egg-info/PKG-INFO
utilitybox.egg-info/SOURCES.txt
utilitybox.egg-info/dependency_links.txt
utilitybox.egg-info/entry_points.txt
utilitybox.egg-info/requires.txt
utilitybox.egg-info/top_level.txt