Metadata-Version: 2.1
Name: utilitybox
Version: 0.0.0.1
Summary: ...
Home-page: https://github.com/Josecolin99/utilitybox
Author: Jose Angel Colin Najera
Author-email: josecolin99@gmail.com
License: MIT
Keywords: utilitybox
Platform: UNKNOWN
Classifier: Development Status :: 3 - Alpha
Classifier: Intended Audience :: Developers
Classifier: Topic :: Software Development :: Build Tools
Classifier: License :: OSI Approved :: MIT License
Classifier: Programming Language :: Python :: 3
